[
    {
        "filename": "../src/topologies/topzoo/Chinanet.gml",
        "result_output": "../out/EXPERIMENT_TOPOLOGY_ZOO_BDD_RUN_4/results/12345494.json",
        "bdd_output": "../out/EXPERIMENT_TOPOLOGY_ZOO_BDD_RUN_4/bdds/12345494.json",
        "replication_output_file_prefix": "../out/EXPERIMENT_TOPOLOGY_ZOO_BDD_RUN_4/data/12345494",
        "seed": 20001,
        "demands": 4,
        "experiment": "gap_free_safe_limited_super_safe",
        "num_paths": 2,
        "par1": "0",
        "par2": "0",
        "par3": "0",
        "par4": "0",
        "par5": "no population",
        "solved": true,
        "size": 16,
        "solve_time": 0.0024203434586524963,
        "all_time": 0.029285170137882233,
        "usage": 30,
        "edge_evaluation": [
            0,
            0,
            0,
            0,
            0,
            0,
            0
        ],
        "query_time": [],
        "gap_free_time": 0.00017571449279785156,
        "time_points": []
    }
]