[
    {
        "filename": "../src/topologies/topzoo/Ion.gml",
        "result_output": "../out/EXPERIMENT_TOPOLOGY_ZOO_BDD_RUN_4/results/12347497.json",
        "bdd_output": "../out/EXPERIMENT_TOPOLOGY_ZOO_BDD_RUN_4/bdds/12347497.json",
        "replication_output_file_prefix": "../out/EXPERIMENT_TOPOLOGY_ZOO_BDD_RUN_4/data/12347497",
        "seed": 20001,
        "demands": 7,
        "experiment": "gap_free_safe_limited_super_safe",
        "num_paths": 2,
        "par1": "0",
        "par2": "0",
        "par3": "0",
        "par4": "0",
        "par5": "no population",
        "solved": true,
        "size": 114022,
        "solve_time": 16.405599907040596,
        "all_time": 16.8258942887187,
        "usage": 31,
        "edge_evaluation": [
            0,
            0,
            0,
            0,
            0,
            0,
            0
        ],
        "query_time": [],
        "gap_free_time": 10.20825458317995,
        "time_points": []
    }
]