[
    {
        "filename": "../src/topologies/topzoo/Garr201109.gml",
        "result_output": "../out/EXPERIMENT_TOPOLOGY_ZOO_BDD_RUN_4/results/12346620.json",
        "bdd_output": "../out/EXPERIMENT_TOPOLOGY_ZOO_BDD_RUN_4/bdds/12346620.json",
        "replication_output_file_prefix": "../out/EXPERIMENT_TOPOLOGY_ZOO_BDD_RUN_4/data/12346620",
        "seed": 20001,
        "demands": 10,
        "experiment": "gap_free_safe_limited_super_safe",
        "num_paths": 2,
        "par1": "0",
        "par2": "0",
        "par3": "0",
        "par4": "0",
        "par5": "no population",
        "solved": true,
        "size": 588399,
        "solve_time": 284.08280251920223,
        "all_time": 292.7714787647128,
        "usage": 30,
        "edge_evaluation": [
            0,
            0,
            0,
            0,
            0,
            0,
            0
        ],
        "query_time": [],
        "gap_free_time": 108.32698015868664,
        "time_points": []
    }
]