[
    {
        "filename": "../src/topologies/topzoo/Grnet.gml",
        "result_output": "../out/EXPERIMENT_TOPOLOGY_ZOO_BDD_RUN_4/results/12346936.json",
        "bdd_output": "../out/EXPERIMENT_TOPOLOGY_ZOO_BDD_RUN_4/bdds/12346936.json",
        "replication_output_file_prefix": "../out/EXPERIMENT_TOPOLOGY_ZOO_BDD_RUN_4/data/12346936",
        "seed": 20001,
        "demands": 6,
        "experiment": "gap_free_safe_limited_super_safe",
        "num_paths": 2,
        "par1": "0",
        "par2": "0",
        "par3": "0",
        "par4": "0",
        "par5": "no population",
        "solved": true,
        "size": 1037,
        "solve_time": 0.6354471147060394,
        "all_time": 0.8213779777288437,
        "usage": 30,
        "edge_evaluation": [
            0,
            0,
            0,
            0,
            0,
            0,
            0
        ],
        "query_time": [],
        "gap_free_time": 0.09794428199529648,
        "time_points": []
    }
]