[
    {
        "filename": "../src/topologies/topzoo/KentmanJan2011.gml",
        "result_output": "../out/EXPERIMENT_CLIQUE_RESIL_RUN_1/results/12502646.json",
        "bdd_output": "../out/EXPERIMENT_CLIQUE_RESIL_RUN_1/bdds/12502646.json",
        "replication_output_file_prefix": "../out/EXPERIMENT_CLIQUE_RESIL_RUN_1/data/12502646",
        "seed": 20001,
        "demands": 6,
        "experiment": "clique_resilience",
        "num_paths": 2,
        "par1": "0",
        "par2": "0",
        "par3": "0",
        "par4": "0",
        "par5": "3",
        "solved": true,
        "size": 26,
        "solve_time": 0.0028760135173797607,
        "all_time": 3.5840384662151337,
        "usage": -1,
        "edge_evaluation": [
            49855,
            76076,
            65.53315105946685,
            175712,
            26221,
            76076,
            100.0
        ],
        "k_link_resillience": 100.0,
        "query_time": [],
        "gap_free_time": 0,
        "time_points": [],
        "usage_times": [],
        "optimize_time": 0.0035776421427726746,
        "subtree_times": [],
        "failover_plus_build_time": 0.0028760135173797607,
        "no_change_query_times": [],
        "no_change_query_solved_times": [],
        "no_change_query_infeasible_counts": [],
        "no_change_query_solved_counts": [],
        "no_change_query_not_solved_but_feasible_counts": [],
        "query_impossible_count": []
    }
]