[
    {
        "filename": "../src/topologies/topzoo/Bellcanada.gml",
        "result_output": "../out/EXPERIMENT_TOPOLOGY_ZOO_SUB_SPECTRUM_RUN_4/results/12436354.json",
        "bdd_output": "../out/EXPERIMENT_TOPOLOGY_ZOO_SUB_SPECTRUM_RUN_4/bdds/12436354.json",
        "replication_output_file_prefix": "../out/EXPERIMENT_TOPOLOGY_ZOO_SUB_SPECTRUM_RUN_4/data/12436354",
        "seed": 20001,
        "demands": 10,
        "experiment": "topozoo_best_subspectrum",
        "num_paths": 2,
        "par1": "0",
        "par2": "0",
        "par3": "0",
        "par4": "0",
        "par5": "no population",
        "solved": true,
        "size": 220,
        "solve_time": 0.18741288036108017,
        "all_time": 0.42397012561559677,
        "usage": 115,
        "edge_evaluation": [
            0,
            0,
            0,
            0,
            0,
            0,
            0
        ],
        "gap_free_time": 0,
        "count_least_changes": [],
        "time_points": [],
        "usage_times": [],
        "par_usage_times": [],
        "query_time": []
    }
]